collector.py
executor.py
expect.py
runner.py
cli/__init__.py
cli/main.py
drserpent-3.0.dist-info/METADATA
drserpent-3.0.dist-info/RECORD
drserpent-3.0.dist-info/WHEEL
drserpent-3.0.dist-info/entry_points.txt
drserpent-3.0.dist-info/top_level.txt
init/context.py
init_example/context.py
init_example/fizzbuzz.py
init_example/test_fizzbuzz.py
scripts/__init__.py
scripts/main.py
