Metadata-Version: 2.1
Name: drserpent
Version: 3.0
Summary: Python Testing Framework
Home-page: https://github.com/DrSerpent/DrSerpent-Core
Author: Tom Betts
Author-email: tom.betts@live.co.uk
License: MIT
Platform: UNKNOWN
Requires-Dist: emoji
Requires-Dist: Click
